[{"Location":"CONSOLATA MISSIONARY SISTERS I","Address":"120 Church St","City":"Sacaton","State":"AZ","Zip":"85147"},{"Location":"GILA RIVER HEALTH CARE #1","Address":"565 West Seed Farm Road","City":"Sacaton","State":"AZ","Zip":"85147"},{"Location":"GILA RIVER INDIAN COMMUN","Address":"525 West Access Road","City":"Sacaton","State":"AZ","Zip":"85147"},{"Location":"GILA RIVER INDIAN COMMUN","Address":"417 South Pear Road","City":"Sacaton","State":"AZ","Zip":"85147"},{"Location":"GILA RIVER INDIAN COMMUNITY","Address":"505 South Pear Road","City":"Sacaton","State":"AZ","Zip":"85147"},{"Location":"GILA RIVER WELLNESS CTR","Address":"420 E Parkway Dr","City":"Sacaton","State":"AZ","Zip":"85147"}]