[{"Location":"HIDDEN VALLEY LAKE ASSOC","Address":"19210 Hartmann Rd","City":"Hidden Valley Lake","State":"CA","Zip":"95467"},{"Location":"STONE FIRE PIZZA COMPANY","Address":"18983 Hartmann Rd","City":"Hidden Valley Lake","State":"CA","Zip":"95467"},{"Location":"HIDDEN VALLEY LAKE ASSOC","Address":"19210 Hartmann Rd","City":"Hidden Valley Lake","State":"CA","Zip":"95467"},{"Location":"STONE FIRE PIZZA COMPANY","Address":"18983 Hartmann Rd","City":"Hidden Valley Lake","State":"CA","Zip":"95467"}]